pandoc_import_code.py
pandoc_import_code-1.0.0.dist-info/METADATA
pandoc_import_code-1.0.0.dist-info/WHEEL
pandoc_import_code-1.0.0.dist-info/entry_points.txt
pandoc_import_code-1.0.0.dist-info/top_level.txt
pandoc_import_code-1.0.0.dist-info/RECORD
