Metadata-Version: 2.1
Name: pandoc-import-code
Version: 1.0.0
Summary: Yet another pandoc filter to include external code files.
Home-page: https://github.com/noelmace/pandoc-import-code
Author: Noël Macé
Author-email: contact@noelmace.com
License: MIT
Platform: UNKNOWN
Classifier: Environment :: Console
Classifier: Intended Audience :: End Users/Desktop
Classifier: Programming Language :: Python
Classifier: License :: OSI Approved :: MIT License
Requires-Dist: panflute (<3,>=2)
Requires-Dist: comment-parser (<2,>=1)
